.travis.yml
NOTICE.txt
README.rst
bootstrap.py
buildout.cfg
eke.specimens.sublime-project
setup.cfg
setup.py
travis.cfg
docs/HISTORY.txt
docs/INSTALL.txt
docs/LICENSE.txt
eke/__init__.py
eke.specimens.egg-info/PKG-INFO
eke.specimens.egg-info/SOURCES.txt
eke.specimens.egg-info/dependency_links.txt
eke.specimens.egg-info/entry_points.txt
eke.specimens.egg-info/namespace_packages.txt
eke.specimens.egg-info/not-zip-safe
eke.specimens.egg-info/requires.txt
eke.specimens.egg-info/top_level.txt
eke/specimens/README.rst
eke/specimens/__init__.py
eke/specimens/config.py
eke/specimens/configure.zcml
eke/specimens/interfaces.py
eke/specimens/overrides.zcml
eke/specimens/testing.py
eke/specimens/upgrades.py
eke/specimens/upgrades.zcml
eke/specimens/utils.py
eke/specimens/browser/__init__.py
eke/specimens/browser/configure.zcml
eke/specimens/browser/ingest.py
eke/specimens/browser/specimen.css
eke/specimens/browser/utils.py
eke/specimens/browser/views.py
eke/specimens/browser/images/active-erne-set.png
eke/specimens/browser/images/case-control-subset.png
eke/specimens/browser/images/erne-specimen-system.png
eke/specimens/browser/images/generic-specimen-set.gif
eke/specimens/browser/images/inactive-erne-set.png
eke/specimens/browser/images/probe-icon.png
eke/specimens/browser/images/specimen-system-folder.gif
eke/specimens/browser/images/specimen-system.gif
eke/specimens/browser/templates/activeerneset.pt
eke/specimens/browser/templates/casecontrolsubset.pt
eke/specimens/browser/templates/ernespecimensystem.pt
eke/specimens/browser/templates/genericspecimenset.pt
eke/specimens/browser/templates/inactiveerneset.pt
eke/specimens/browser/templates/ingestresults.pt
eke/specimens/browser/templates/specimensystem.pt
eke/specimens/browser/templates/specimensystemfolder.pt
eke/specimens/content/__init__.py
eke/specimens/content/activeerneset.py
eke/specimens/content/base.py
eke/specimens/content/casecontrolsubset.py
eke/specimens/content/configure.zcml
eke/specimens/content/ernespecimensystem.py
eke/specimens/content/genericspecimenset.py
eke/specimens/content/inactiveerneset.py
eke/specimens/content/specimensystem.py
eke/specimens/content/specimensystemfolder.py
eke/specimens/data/offline-site-specimen-summaries.zexp
eke/specimens/data/reference-sets.zexp
