Metadata-Version: 2.1
Name: eke.specimens
Version: 1.1.12
Summary: ERNE Specimen Management for the EDRN Knowledge Environment
Home-page: https://github.com/EDRN/eke.specimens
Author: Andrew Hart
Author-email: andrew.hart@jpl.nasa.gov
License: ALv2
Keywords: web zope plone edrn cancer biomarkers eke knowledge specimen erne
Platform: UNKNOWN
Classifier: Development Status :: 4 - Beta
Classifier: Environment :: Web Environment
Classifier: Framework :: Plone
Classifier: Intended Audience :: Healthcare Industry
Classifier: Intended Audience :: Science/Research
Classifier: License :: OSI Approved :: Apache Software License
Classifier: Operating System :: OS Independent
Classifier: Programming Language :: Python
Classifier: Topic :: Internet :: WWW/HTTP
Classifier: Topic :: Internet :: Z39.50
Classifier: Topic :: Scientific/Engineering :: Bio-Informatics
Classifier: Topic :: Software Development :: Libraries :: Python Modules
Provides-Extra: test
